setup.py
basharmor/.load
basharmor/__init__.py
basharmor/basharmor.py
basharmor/obsf.py
basharmor.egg-info/PKG-INFO
basharmor.egg-info/SOURCES.txt
basharmor.egg-info/dependency_links.txt
basharmor.egg-info/entry_points.txt
basharmor.egg-info/requires.txt
basharmor.egg-info/top_level.txt