Metadata-Version: 2.1
Name: basharmor
Version: 3.1.0
Summary: A Python module for installing and configuring Basharmor
Home-page: https://github.com/Azigaming404
Author: Aji Permana
Author-email: admin@cybervpn.site
Classifier: Programming Language :: Python :: 3
Classifier: License :: OSI Approved :: MIT License
Classifier: Operating System :: OS Independent
Requires-Dist: requests
Requires-Dist: pyinstaller
